[
    {
        "id": "p-sub-menclothing-sleeveless-1",
        "title": "Sleeveless Hoodies Sample 1",
        "price": 599,
        "originalPrice": 1199,
        "image": "https://picsum.photos/seed/sub-menclothing-sleeveless1/400/400",
        "rating": "4.2",
        "reviewCount": 196,
        "color": "White",
        "availableSizes": [
            "S",
            "M",
            "L",
            "XL"
        ],
        "badge": null,
        "can_beCustomised": 1
    },
    {
        "id": "p-sub-menclothing-sleeveless-2",
        "title": "Sleeveless Hoodies Sample 2",
        "price": 599,
        "originalPrice": 1199,
        "image": "https://picsum.photos/seed/sub-menclothing-sleeveless2/400/400",
        "rating": "4.2",
        "reviewCount": 166,
        "color": "White",
        "availableSizes": [
            "S",
            "M",
            "L",
            "XL"
        ],
        "badge": null,
        "can_beCustomised": 1
    },
    {
        "id": "p-sub-menclothing-sleeveless-3",
        "title": "Sleeveless Hoodies Sample 3",
        "price": 599,
        "originalPrice": 1199,
        "image": "https://picsum.photos/seed/sub-menclothing-sleeveless3/400/400",
        "rating": "4.2",
        "reviewCount": 181,
        "color": "White",
        "availableSizes": [
            "S",
            "M",
            "L",
            "XL"
        ],
        "badge": "Bestseller",
        "can_beCustomised": 1
    },
    {
        "id": "p-sub-menclothing-sleeveless-4",
        "title": "Sleeveless Hoodies Sample 4",
        "price": 599,
        "originalPrice": 1199,
        "image": "https://picsum.photos/seed/sub-menclothing-sleeveless4/400/400",
        "rating": "4.2",
        "reviewCount": 67,
        "color": "White",
        "availableSizes": [
            "S",
            "M",
            "L",
            "XL"
        ],
        "badge": "New Arrival",
        "can_beCustomised": 1
    },
    {
        "id": "p-sub-menclothing-sleeveless-5",
        "title": "Sleeveless Hoodies Sample 5",
        "price": 599,
        "originalPrice": 1199,
        "image": "https://picsum.photos/seed/sub-menclothing-sleeveless5/400/400",
        "rating": "4.2",
        "reviewCount": 182,
        "color": "White",
        "availableSizes": [
            "S",
            "M",
            "L",
            "XL"
        ],
        "badge": null,
        "can_beCustomised": 1
    },
    {
        "id": "p-sub-menclothing-sleeveless-6",
        "title": "Sleeveless Hoodies Sample 6",
        "price": 599,
        "originalPrice": 1199,
        "image": "https://picsum.photos/seed/sub-menclothing-sleeveless6/400/400",
        "rating": "4.2",
        "reviewCount": 96,
        "color": "White",
        "availableSizes": [
            "S",
            "M",
            "L",
            "XL"
        ],
        "badge": "Bestseller",
        "can_beCustomised": 1
    },
    {
        "id": "p-sub-menclothing-sleeveless-7",
        "title": "Sleeveless Hoodies Sample 7",
        "price": 599,
        "originalPrice": 1199,
        "image": "https://picsum.photos/seed/sub-menclothing-sleeveless7/400/400",
        "rating": "4.2",
        "reviewCount": 85,
        "color": "White",
        "availableSizes": [
            "S",
            "M",
            "L",
            "XL"
        ],
        "badge": null,
        "can_beCustomised": 1
    },
    {
        "id": "p-sub-menclothing-sleeveless-8",
        "title": "Sleeveless Hoodies Sample 8",
        "price": 599,
        "originalPrice": 1199,
        "image": "https://picsum.photos/seed/sub-menclothing-sleeveless8/400/400",
        "rating": "4.2",
        "reviewCount": 53,
        "color": "White",
        "availableSizes": [
            "S",
            "M",
            "L",
            "XL"
        ],
        "badge": "New Arrival",
        "can_beCustomised": 1
    }
]