[
    {
        "id": "sub-minimalist-0",
        "sku_id": "SKU-SUBMINIMALIST0",
        "title": "Minimalistic Oversized Hip Hop Customized Printed Men’s Half Sleeves Cotton T-Shirt",
        "description": "Classic half-sleeve Minimalist, perfect for everyday wear. Minimalistic Oversized Hip Hop Customized Printed Men’s Half Sleeves Cotton T-Shirt",
        "price": 599,
        "originalPrice": 1331,
        "rating": "4.0",
        "reviewCount": 771,
        "color": "Black",
        "availableSizes": [
            "S",
            "M",
            "L",
            "XL",
            "XXL"
        ],
        "badge": "55% OFF",
        "image": "https://static.yourprint.in/new-admin-ajax.php?action=resize_outer_image&cfcache=all&url=med-s3%2Fd-i-o%2FTshirts%2FMen%2Ftshirt_hs_oversized_men_pat_d119_o.jpg&resizeTo=450&format=webp",
        "can_beCustomised": 1,
        "tags": [
            "Customizable",
            "Printed",
            "Half Sleeve",
            "Oversized",
            "Men"
        ],
        "status": "Special Offer",
        "features": {
            "fabric": "100% Cotton",
            "fit": "Oversized Fit",
            "sleeve": "Half Sleeve",
            "pattern": "Graphic Print"
        }
    },
    {
        "id": "sub-minimalist-1",
        "sku_id": "SKU-SUBMINIMALIST1",
        "title": "Minimalistic Name Customized Printed Men’s Half Sleeves Cotton T-Shirt",
        "description": "Classic half-sleeve Minimalist, perfect for everyday wear. Minimalistic Name Customized Printed Men’s Half Sleeves Cotton T-Shirt",
        "price": 449,
        "originalPrice": 898,
        "rating": "4.5",
        "reviewCount": 485,
        "color": "Black",
        "availableSizes": [
            "S",
            "M",
            "L",
            "XL",
            "XXL"
        ],
        "badge": "50% OFF",
        "image": "https://static.yourprint.in/new-admin-ajax.php?action=resize_outer_image&cfcache=all&url=med-s3%2Fd-i-o%2FTshirts%2FMen%2Ftshirt_hs_men_pat_d169_o.jpg&resizeTo=450&format=webp",
        "can_beCustomised": 1,
        "tags": [
            "Customizable",
            "Printed",
            "Half Sleeve",
            "Men"
        ],
        "status": "",
        "features": {
            "fabric": "100% Cotton",
            "fit": "Regular Fit",
            "sleeve": "Half Sleeve",
            "pattern": "Graphic Print"
        }
    },
    {
        "id": "sub-minimalist-2",
        "sku_id": "SKU-SUBMINIMALIST2",
        "title": "Minimalistic Customized Printed Men’s Half Sleeves Cotton T-Shirt",
        "description": "Classic half-sleeve Minimalist, perfect for everyday wear. Minimalistic Customized Printed Men’s Half Sleeves Cotton T-Shirt",
        "price": 499,
        "originalPrice": 998,
        "rating": "4.5",
        "reviewCount": 533,
        "color": "Free Color",
        "availableSizes": [
            "S",
            "M",
            "L",
            "XL",
            "XXL"
        ],
        "badge": "50% OFF",
        "image": "https://static.yourprint.in/new-admin-ajax.php?action=resize_outer_image&cfcache=all&url=med-s3%2Fd-i-o%2FTshirts%2FMen%2Ftshirt_hs_men_pat_d119_o.jpg&resizeTo=450&format=webp",
        "can_beCustomised": 1,
        "tags": [
            "Customizable",
            "Printed",
            "Half Sleeve",
            "Men"
        ],
        "status": "",
        "features": {
            "fabric": "100% Cotton",
            "fit": "Regular Fit",
            "sleeve": "Half Sleeve",
            "pattern": "Graphic Print"
        }
    },
    {
        "id": "sub-minimalist-3",
        "sku_id": "SKU-SUBMINIMALIST3",
        "title": "Minimalistic Name V Neck Customized Printed Men’s Half Sleeves Cotton T-Shirt",
        "description": "Classic half-sleeve Minimalist, perfect for everyday wear. Minimalistic Name V Neck Customized Printed Men’s Half Sleeves Cotton T-Shirt",
        "price": 499,
        "originalPrice": 998,
        "rating": "4.3",
        "reviewCount": 702,
        "color": "Free Color",
        "availableSizes": [
            "S",
            "M",
            "L",
            "XL",
            "XXL"
        ],
        "badge": "50% OFF",
        "image": "https://static.yourprint.in/new-admin-ajax.php?action=resize_outer_image&cfcache=all&url=med-s3%2Fd-i-o%2FTshirts%2FMen%2Ftshirt_hs_vneck_men_pat_d169_o.jpg&resizeTo=450&format=webp",
        "can_beCustomised": 1,
        "tags": [
            "Customizable",
            "Printed",
            "Half Sleeve",
            "Men"
        ],
        "status": "",
        "features": {
            "fabric": "100% Cotton",
            "fit": "Regular Fit",
            "sleeve": "Half Sleeve",
            "pattern": "Graphic Print"
        }
    },
    {
        "id": "sub-minimalist-4",
        "sku_id": "SKU-SUBMINIMALIST4",
        "title": "Minimalistic V Neck Customized Printed Men’s Half Sleeves Cotton T-Shirt",
        "description": "Classic half-sleeve Minimalist, perfect for everyday wear. Minimalistic V Neck Customized Printed Men’s Half Sleeves Cotton T-Shirt",
        "price": 499,
        "originalPrice": 998,
        "rating": "4.4",
        "reviewCount": 129,
        "color": "Black",
        "availableSizes": [
            "S",
            "M",
            "L",
            "XL",
            "XXL"
        ],
        "badge": "50% OFF",
        "image": "https://static.yourprint.in/new-admin-ajax.php?action=resize_outer_image&cfcache=all&url=med-s3%2Fd-i-o%2FTshirts%2FMen%2Ftshirt_hs_vneck_men_pat_d119_o.jpg&resizeTo=450&format=webp",
        "can_beCustomised": 1,
        "tags": [
            "Customizable",
            "Printed",
            "Half Sleeve",
            "Men"
        ],
        "status": "",
        "features": {
            "fabric": "100% Cotton",
            "fit": "Regular Fit",
            "sleeve": "Half Sleeve",
            "pattern": "Graphic Print"
        }
    },
    {
        "id": "sub-minimalist-5",
        "sku_id": "SKU-SUBMINIMALIST5",
        "title": "Minimalistic Name Oversized Hip Hop Customized Printed Men’s Half Sleeves Cotton T-Shirt",
        "description": "Classic half-sleeve Minimalist, perfect for everyday wear. Minimalistic Name Oversized Hip Hop Customized Printed Men’s Half Sleeves Cotton T-Shirt",
        "price": 599,
        "originalPrice": 1331,
        "rating": "4.0",
        "reviewCount": 526,
        "color": "Free Color",
        "availableSizes": [
            "S",
            "M",
            "L",
            "XL",
            "XXL"
        ],
        "badge": "55% OFF",
        "image": "https://static.yourprint.in/new-admin-ajax.php?action=resize_outer_image&cfcache=all&url=med-s3%2Fd-i-o%2FTshirts%2FMen%2Ftshirt_hs_oversized_men_pat_d169_o.jpg&resizeTo=450&format=webp",
        "can_beCustomised": 1,
        "tags": [
            "Customizable",
            "Printed",
            "Half Sleeve",
            "Oversized",
            "Men"
        ],
        "status": "Special Offer",
        "features": {
            "fabric": "100% Cotton",
            "fit": "Oversized Fit",
            "sleeve": "Half Sleeve",
            "pattern": "Graphic Print"
        }
    }
]